privat_exchange_rates/__init__.py
privat_exchange_rates/exchange_rates.py
privat_exchange_rates-0.0.2.dist-info/LICENSE
privat_exchange_rates-0.0.2.dist-info/METADATA
privat_exchange_rates-0.0.2.dist-info/WHEEL
privat_exchange_rates-0.0.2.dist-info/top_level.txt
privat_exchange_rates-0.0.2.dist-info/RECORD
