Metadata-Version: 2.1
Name: privat-exchange-rates
Version: 0.0.2
Summary: A small library for getting information on cash exchange rates of PrivatBank and the NBU on the selected date
Home-page: UNKNOWN
Author: Valentyn Khoroshchak
Author-email: valentin.khoroshchak@gmail.com
License: MIT
Project-URL: Source, https://github.com/ValentynKhoroshchak/privat-exchange-rates
Keywords: python,exchange rate,privatbank
Platform: UNKNOWN
Classifier: Intended Audience :: Education
Classifier: Programming Language :: Python :: 3
Classifier: License :: OSI Approved :: MIT License
Classifier: Operating System :: OS Independent
Requires-Dist: requests
